<?xml version="1.0" encoding="utf-8" ?><dwsync><file name="0.wav" server="ftp.juanalcantara.com/public_html/" local="3600712449" remote="321595785925613888" Dst="-1" /><file name="1.wav" server="ftp.juanalcantara.com/public_html/" local="3600712449" remote="321595785925613888" Dst="-1" /><file name="10.wav" server="ftp.juanalcantara.com/public_html/" local="3600712449" remote="321595785925613888" Dst="-1" /><file name="11.wav" server="ftp.juanalcantara.com/public_html/" local="3600712449" remote="321595785925613888" Dst="-1" /><file name="12.wav" server="ftp.juanalcantara.com/public_html/" local="3600712449" remote="321595785925613888" Dst="-1" /><file name="14.wav" server="ftp.juanalcantara.com/public_html/" local="3600712450" remote="321595785925613888" Dst="-1" /><file name="13.wav" server="ftp.juanalcantara.com/public_html/" local="3600712450" remote="321595785925613888" Dst="-1" /><file name="15.wav" server="ftp.juanalcantara.com/public_html/" local="3600712450" remote="321595785925613888" Dst="-1" /><file name="16.wav" server="ftp.juanalcantara.com/public_html/" local="3600712450" remote="321595785925613888" Dst="-1" /><file name="17.wav" server="ftp.juanalcantara.com/public_html/" local="3600712450" remote="321595785925613888" Dst="-1" /><file name="18.wav" server="ftp.juanalcantara.com/public_html/" local="3600712450" remote="321595785925613888" Dst="-1" /><file name="19.wav" server="ftp.juanalcantara.com/public_html/" local="3600712450" remote="321595785925613888" Dst="-1" /><file name="20.wav" server="ftp.juanalcantara.com/public_html/" local="3600712450" remote="321595785925613888" Dst="-1" /><file name="2.wav" server="ftp.juanalcantara.com/public_html/" local="3600712450" remote="321595785925613888" Dst="-1" /><file name="3.wav" server="ftp.juanalcantara.com/public_html/" local="3600712450" remote="321595785925613888" Dst="-1" /><file name="4.wav" server="ftp.juanalcantara.com/public_html/" local="3600712450" remote="321595785925613888" Dst="-1" /><file name="5.wav" server="ftp.juanalcantara.com/public_html/" local="3600712450" remote="321595785925613888" Dst="-1" /><file name="6.wav" server="ftp.juanalcantara.com/public_html/" local="3600712450" remote="321595785925613888" Dst="-1" /><file name="8.wav" server="ftp.juanalcantara.com/public_html/" local="3600712450" remote="321595785925613888" Dst="-1" /><file name="7.wav" server="ftp.juanalcantara.com/public_html/" local="3600712450" remote="321595785925613888" Dst="-1" /><file name="A.wav" server="ftp.juanalcantara.com/public_html/" local="3600712451" remote="321595785925613888" Dst="-1" /><file name="9.wav" server="ftp.juanalcantara.com/public_html/" local="3600712451" remote="321595785925613888" Dst="-1" /><file name="B.wav" server="ftp.juanalcantara.com/public_html/" local="3600712451" remote="321595785925613888" Dst="-1" /><file name="C.wav" server="ftp.juanalcantara.com/public_html/" local="3600712451" remote="321595785925613888" Dst="-1" /><file name="D.wav" server="ftp.juanalcantara.com/public_html/" local="3600712451" remote="321595785925613888" Dst="-1" /><file name="E.wav" server="ftp.juanalcantara.com/public_html/" local="3600712451" remote="321595785925613888" Dst="-1" /><file name="G.wav" server="ftp.juanalcantara.com/public_html/" local="3600712451" remote="321595785925613888" Dst="-1" /><file name="F.wav" server="ftp.juanalcantara.com/public_html/" local="3600712451" remote="321595785925613888" Dst="-1" /><file name="H.wav" server="ftp.juanalcantara.com/public_html/" local="3600712451" remote="321595785925613888" Dst="-1" /><file name="I.wav" server="ftp.juanalcantara.com/public_html/" local="3600712451" remote="321595785925613888" Dst="-1" /><file name="J.wav" server="ftp.juanalcantara.com/public_html/" local="3600712451" remote="321595785925613888" Dst="-1" /><file name="K.wav" server="ftp.juanalcantara.com/public_html/" local="3600712451" remote="321595785925613888" Dst="-1" /><file name="M.wav" server="ftp.juanalcantara.com/public_html/" local="3600712451" remote="321595785925613888" Dst="-1" /><file name="L.wav" server="ftp.juanalcantara.com/public_html/" local="3600712451" remote="321595785925613888" Dst="-1" /><file name="MINUS.wav" server="ftp.juanalcantara.com/public_html/" local="3600712451" remote="321595785925613888" Dst="-1" /><file name="N.wav" server="ftp.juanalcantara.com/public_html/" local="3600712451" remote="321595785925613888" Dst="-1" /><file name="O.wav" server="ftp.juanalcantara.com/public_html/" local="3600712451" remote="321595785925613888" Dst="-1" /><file name="P.wav" server="ftp.juanalcantara.com/public_html/" local="3600712451" remote="321595785925613888" Dst="-1" /><file name="PLUS.wav" server="ftp.juanalcantara.com/public_html/" local="3600712451" remote="321595785925613888" Dst="-1" /><file name="Q.wav" server="ftp.juanalcantara.com/public_html/" local="3600712451" remote="321595785925613888" Dst="-1" /><file name="S.wav" server="ftp.juanalcantara.com/public_html/" local="3600712452" remote="321595785925613888" Dst="-1" /><file name="T.wav" server="ftp.juanalcantara.com/public_html/" local="3600712452" remote="321595785925613888" Dst="-1" /><file name="R.wav" server="ftp.juanalcantara.com/public_html/" local="3600712452" remote="321595785925613888" Dst="-1" /><file name="U.wav" server="ftp.juanalcantara.com/public_html/" local="3600712452" remote="321595785925613888" Dst="-1" /><file name="TIMES.wav" server="ftp.juanalcantara.com/public_html/" local="3600712452" remote="321595785925613888" Dst="-1" /><file name="V.wav" server="ftp.juanalcantara.com/public_html/" local="3600712452" remote="321595785925613888" Dst="-1" /><file name="W.wav" server="ftp.juanalcantara.com/public_html/" local="3600712452" remote="321595785925613888" Dst="-1" /><file name="X.wav" server="ftp.juanalcantara.com/public_html/" local="3600712452" remote="321595785925613888" Dst="-1" /><file name="Y.wav" server="ftp.juanalcantara.com/public_html/" local="3600712452" remote="321595785925613888" Dst="-1" /><file name="Z.wav" server="ftp.juanalcantara.com/public_html/" local="3600712452" remote="321595785925613888" Dst="-1" /><file name="error.wav" server="ftp.juanalcantara.com/public_html/" local="3600712452" remote="321595785925613888" Dst="-1" /></dwsync>